zunzuncito/__init__.py
zunzuncito/http_status_codes.py
zunzuncito/request.py
zunzuncito/response.py
zunzuncito/tools.py
zunzuncito/version.py
zunzuncito/zunzun.py
zunzuncito-0.1.20.dist-info/DESCRIPTION.rst
zunzuncito-0.1.20.dist-info/METADATA
zunzuncito-0.1.20.dist-info/pydist.json
zunzuncito-0.1.20.dist-info/RECORD
zunzuncito-0.1.20.dist-info/top_level.txt
zunzuncito-0.1.20.dist-info/WHEEL
