Metadata-Version: 2.0
Name: zunzuncito
Version: 0.1.20
Summary: A micro-framework for creating REST API's
Home-page: http://www.zunzun.io
Author: Nicolas Embriz
Author-email: nbari@dalmp.com
License: BSD
Download-URL: https://github.com/nbari/zunzuncito/tarball/master
Keywords: wsgi web api framework rest http
Platform: any
Classifier: Development Status :: 4 - Beta
Classifier: Environment :: Console
Classifier: Environment :: Web Environment
Classifier: Intended Audience :: Developers
Classifier: Intended Audience :: System Administrators
Classifier: License :: OSI Approved :: BSD License
Classifier: Operating System :: OS Independent
Classifier: Programming Language :: Python
Classifier: Programming Language :: Python :: 2.7
Classifier: Topic :: Internet :: WWW/HTTP :: WSGI
Classifier: Topic :: Software Development :: Libraries :: Application Frameworks
